psychopy_phidgets/__init__.py
psychopy_phidgets/phidgets.py
psychopy_phidgets/component/__init__.py
psychopy_phidgets/component/phidgets.py
psychopy_phidgets/component/classic/phidgets.png
psychopy_phidgets/component/classic/phidgets@2x.png
psychopy_phidgets/component/dark/phidgets.png
psychopy_phidgets/component/dark/phidgets@2x.png
psychopy_phidgets/component/light/phidgets.png
psychopy_phidgets/component/light/phidgets@2x.png
psychopy_phidgets/experiment/components/phidgets/__init__.py
psychopy_phidgets/experiment/components/phidgets/phidgets.py
psychopy_phidgets/experiment/components/phidgets/classic/phidgets.png
psychopy_phidgets/experiment/components/phidgets/classic/phidgets@2x.png
psychopy_phidgets/experiment/components/phidgets/dark/phidgets.png
psychopy_phidgets/experiment/components/phidgets/dark/phidgets@2x.png
psychopy_phidgets/experiment/components/phidgets/light/phidgets.png
psychopy_phidgets/experiment/components/phidgets/light/phidgets@2x.png
psychopy_phidgets/hardware/__init__.py
psychopy_phidgets/hardware/phidgets.py
psychopy_phidgets-0.2.3.dist-info/LICENSE
psychopy_phidgets-0.2.3.dist-info/METADATA
psychopy_phidgets-0.2.3.dist-info/WHEEL
psychopy_phidgets-0.2.3.dist-info/entry_points.txt
psychopy_phidgets-0.2.3.dist-info/top_level.txt
psychopy_phidgets-0.2.3.dist-info/RECORD
